server/__init__.py
server/async_server.py
server/custrom_server_exceptions.py
server/server_gui.py
server/serverstorage.py
server/common/__init__.py
server/common/utils.py
server/common/variables.py
messenger_server_serg-0.0.1.dist-info/METADATA
messenger_server_serg-0.0.1.dist-info/WHEEL
messenger_server_serg-0.0.1.dist-info/top_level.txt
messenger_server_serg-0.0.1.dist-info/RECORD
