Metadata-Version: 2.1
Name: messenger-server-serg
Version: 0.0.1
Summary: Server
Author: Sergei Metelskiy
Author-email: serguchers@gmail.com
License: UNKNOWN
Platform: UNKNOWN
Requires-Dist: PyQt5
Requires-Dist: sqlalchemy
Requires-Dist: pycryptodome
Requires-Dist: pycryptodomex
